{"name":"Untitled Game","startingBoard":"Untitled","author":"Mark McIntyre","boards":[{"name":"Untitled","playerX":20,"playerY":7,"width":40,"height":15,"tiles":[{"type":"Wall","color":"0E"},{"type":"Wall","color":"0E"},{"type":"Wall","color":"0E"},{"type":"Wall","color":"0E"},{"type":"Wall","color":"0E"},{"type":"Wall","color":"0E"},{"type":"Wall","color":"0E"},{"type":"Wall","color":"0E"},{"type":"Wall","color":"0E"},{"type":"Wall","color":"0E"},{"type":"Wall","color":"0E"},{"type":"Wall","color":"0E"},{"type":"Wall","color":"0E"},{"type":"Wall","color":"0E"},{"type":"Wall","color":"0E"},{"type":"Wall","color":"0E"},{"type":"Wall","color":"0E"},{"type":"Wall","color":"0E"},{"type":"Wall","color":"0E"},{"type":"Wall","color":"0E"},{"type":"Wall","color":"0E"},{"type":"Wall","color":"0E"},{"type":"Wall","color":"0E"},{"type":"Wall","color":"0E"},{"type":"Wall","color":"0E"},{"type":"Wall","color":"0E"},{"type":"Wall","color":"0E"},{"type":"Wall","color":"0E"},{"type":"Wall","color":"0E"},{"type":"Wall","color":"0E"},{"type":"Wall","color":"0E"},{"type":"Wall","color":"0E"},{"type":"Wall","color":"0E"},{"type":"Wall","color":"0E"},{"type":"Wall","color":"0E"},{"type":"Wall","color":"0E"},{"type":"Wall","color":"0E"},{"type":"Wall","color":"0E"},{"type":"Wall","color":"0E"},{"type":"Wall","color":"0E"},{"type":"Wall","color":"0E"},{},{},{},{},{},{},{},{},{},{},{},{},{},{},{},{},{},{},{},{},{},{},{},{},{},{},{},{},{},{"type":"SpiderWeb","color":"08"},{},{"type":"Pusher","color":"0E","speed":3,"orientation":"South"},{},{},{},{},{"type":"SpiderWeb","color":"08"},{},{"type":"Wall","color":"0E"},{"type":"Wall","color":"0E"},{},{},{},{},{},{},{},{},{},{},{},{"type":"Water","color":"F9"},{"type":"Water","color":"F9"},{"type":"Water","color":"F9"},{"type":"Water","color":"F9"},{"type":"Water","color":"F9"},{},{"type":"Forest","color":"20"},{"type":"Forest","color":"20"},{"type":"Forest","color":"20"},{"type":"Forest","color":"20"},{"type":"Forest","color":"20"},{},{"type":"Water","color":"F9"},{"type":"Water","color":"F9"},{"type":"Water","color":"F9"},{"type":"Water","color":"F9"},{"type":"Water","color":"F9"},{},{"type":"SpiderWeb","color":"08"},{"type":"Spider","color":"0C","speed":1,"under":{"type":"SpiderWeb","color":"08"}},{"type":"SliderEw","color":"0E"},{},{},{"type":"SpiderWeb","color":"08"},{"type":"SpiderWeb","color":"08"},{"type":"SpiderWeb","color":"08"},{},{"type":"Wall","color":"0E"},{"type":"Wall","color":"0E"},{},{},{},{},{},{},{},{},{},{},{},{"type":"Water","color":"F9"},{"type":"Water","color":"F9"},{"type":"Water","color":"F9"},{"type":"Water","color":"F9"},{"type":"Water","color":"F9"},{},{"type":"Forest","color":"20"},{"type":"Forest","color":"20"},{"type":"Forest","color":"20"},{"type":"Forest","color":"20"},{"type":"Forest","color":"20"},{},{"type":"Water","color":"F9"},{"type":"Water","color":"F9"},{"type":"Water","color":"F9"},{"type":"Water","color":"F9"},{"type":"Water","color":"F9"},{},{"type":"SpiderWeb","color":"08"},{"type":"SpiderWeb","color":"08"},{"type":"SpiderWeb","color":"08"},{"type":"SpiderWeb","color":"08"},{"type":"SpiderWeb","color":"08"},{"type":"SpiderWeb","color":"08"},{"type":"SpiderWeb","color":"08"},{"type":"SpiderWeb","color":"08"},{},{"type":"Wall","color":"0E"},{"type":"Wall","color":"0E"},{},{},{},{},{},{},{},{},{},{},{},{},{},{},{},{},{},{},{},{},{},{},{},{},{},{},{"type":"SpiderWeb","color":"08"},{"type":"SpiderWeb","color":"08"},{"type":"SpiderWeb","color":"08"},{"type":"SpiderWeb","color":"08"},{"type":"SpiderWeb","color":"08"},{"type":"Boulder","color":"0E"},{},{},{"type":"Spider","color":"0C","speed":1,"under":{"type":"SpiderWeb","color":"08"}},{"type":"SpiderWeb","color":"08"},{"type":"SpiderWeb","color":"08"},{"type":"SpiderWeb","color":"08"},{"type":"Wall","color":"0E"},{"type":"Wall","color":"0E"},{},{"type":"SliderEw","color":"0E"},{"type":"SliderEw","color":"0E"},{"type":"SliderEw","color":"0E"},{"type":"SliderEw","color":"0E"},{"type":"SliderNs","color":"0E"},{},{},{},{},{},{"type":"SolidWall","color":"0E"},{"type":"SolidWall","color":"0E"},{"type":"SolidWall","color":"0E"},{"type":"SolidWall","color":"0E"},{"type":"SolidWall","color":"0E"},{},{"type":"Wall","color":"0E"},{"type":"Wall","color":"0E"},{"type":"BreakableWall","color":"0B"},{"type":"Wall","color":"0E"},{"type":"Wall","color":"0E"},{},{"type":"SolidWall","color":"0E"},{"type":"SolidWall","color":"0E"},{"type":"SolidWall","color":"0E"},{"type":"SolidWall","color":"0E"},{"type":"SolidWall","color":"0E"},{},{},{},{},{},{"type":"SpiderWeb","color":"08"},{"type":"SpiderWeb","color":"08"},{"type":"SpiderWeb","color":"08"},{"type":"Spider","color":"0C","speed":1,"under":{"type":"SpiderWeb","color":"08"}},{"type":"SpiderWeb","color":"08"},{"type":"Wall","color":"0E"},{"type":"Wall","color":"0E"},{},{"type":"SliderNs","color":"0E"},{"type":"Ammo","color":"03"},{"type":"Ammo","color":"03"},{"type":"Ammo","color":"03"},{"type":"SliderNs","color":"0E"},{},{},{},{},{},{"type":"SolidWall","color":"0E"},{"type":"Centipede","color":"09","speed":3},{"type":"Centipede","color":"09","speed":3},{"type":"Centipede","color":"09","speed":3},{"type":"SolidWall","color":"0E"},{},{"type":"Wall","color":"0E"},{"type":"Ammo","color":"03"},{"type":"Ammo","color":"03"},{"type":"Ammo","color":"03"},{"type":"Wall","color":"0E"},{},{"type":"SolidWall","color":"0E"},{"type":"Lion","color":"0C","speed":2},{"type":"Lion","color":"0C","speed":2},{"type":"Lion","color":"0C","speed":2},{"type":"SolidWall","color":"0E"},{},{},{},{"type":"Gem","color":"0D"},{},{},{"type":"SpiderWeb","color":"08"},{"type":"SpiderWeb","color":"08"},{"type":"SpiderWeb","color":"08"},{"type":"SpiderWeb","color":"08"},{"type":"Wall","color":"0E"},{"type":"Wall","color":"0E"},{},{"type":"SliderNs","color":"0E"},{"type":"Ammo","color":"03"},{"type":"Ammo","color":"03"},{"type":"Ammo","color":"03"},{"type":"SliderNs","color":"0E"},{},{},{},{},{},{"type":"SolidWall","color":"0E"},{"type":"Centipede","color":"09","speed":3},{"type":"Water","color":"F9"},{"type":"Centipede","color":"09","speed":3},{"type":"BreakableWall","color":"0B"},{},{"type":"Wall","color":"0E"},{},{"color":"1F","speed":1},{},{"type":"Wall","color":"0E"},{},{"type":"BreakableWall","color":"0B"},{"type":"Lion","color":"0C","speed":2},{"type":"Lion","color":"0C","speed":2},{"type":"Lion","color":"0C","speed":2},{"type":"SolidWall","color":"0E"},{},{},{},{"type":"Gem","color":"0D"},{},{},{"type":"Spider","color":"0C","speed":1,"under":{"type":"SpiderWeb","color":"08"}},{"type":"SpiderWeb","color":"08"},{"type":"SpiderWeb","color":"08"},{"type":"SpiderWeb","color":"08"},{"type":"Wall","color":"0E"},{"type":"Wall","color":"0E"},{},{"type":"Boulder","color":"0E"},{"type":"SliderEw","color":"0E"},{"type":"SliderEw","color":"0E"},{"type":"SliderEw","color":"0E"},{"type":"SliderEw","color":"0E"},{},{},{},{},{},{"type":"SolidWall","color":"0E"},{"type":"Centipede","color":"09","speed":3},{"type":"Centipede","color":"09","speed":3},{},{"type":"SolidWall","color":"0E"},{},{"type":"Wall","color":"0E"},{},{},{},{"type":"Wall","color":"0E"},{},{"type":"SolidWall","color":"0E"},{"type":"Lion","color":"0C","speed":2},{"type":"Lion","color":"0C","speed":2},{"type":"Lion","color":"0C","speed":2},{"type":"SolidWall","color":"0E"},{},{},{},{},{},{"type":"SpiderWeb","color":"08"},{"type":"SpiderWeb","color":"08"},{"type":"SpiderWeb","color":"08"},{"type":"SpiderWeb","color":"08"},{"type":"SpiderWeb","color":"08"},{"type":"Wall","color":"0E"},{"type":"Wall","color":"0E"},{},{},{},{},{},{},{},{},{},{},{},{"type":"SolidWall","color":"0E"},{"type":"SolidWall","color":"0E"},{"type":"SolidWall","color":"0E"},{"type":"SolidWall","color":"0E"},{"type":"SolidWall","color":"0E"},{"type":"InvisibleWall","color":"0A"},{"type":"Wall","color":"0E"},{"type":"Wall","color":"0E"},{"type":"FakeWall","color":"0E"},{"type":"Wall","color":"0E"},{"type":"Wall","color":"0E"},{"type":"InvisibleWall","color":"0A"},{"type":"SolidWall","color":"0E"},{"type":"SolidWall","color":"0E"},{"type":"SolidWall","color":"0E"},{"type":"SolidWall","color":"0E"},{"type":"SolidWall","color":"0E"},{},{},{},{"type":"SliderEw","color":"0E"},{},{"type":"SpiderWeb","color":"08"},{},{},{"type":"SpiderWeb","color":"08"},{"type":"SpiderWeb","color":"08"},{"type":"Wall","color":"0E"},{"type":"Wall","color":"0E"},{},{},{},{},{},{},{},{},{},{},{},{},{},{},{},{"type":"InvisibleWall","color":"0A"},{},{},{},{},{},{},{},{"type":"InvisibleWall","color":"0A"},{},{},{},{},{},{},{},{},{},{},{},{},{"type":"SpiderWeb","color":"08"},{},{"type":"Wall","color":"0E"},{"type":"LineWall","color":"0E"},{"type":"LineWall","color":"0E"},{"type":"LineWall","color":"0E"},{"type":"LineWall","color":"0E"},{"type":"LineWall","color":"0E"},{"type":"LineWall","color":"0E"},{"type":"Boulder","color":"0E"},{"type":"LineWall","color":"0E"},{"type":"LineWall","color":"0E"},{"type":"LineWall","color":"0E"},{"type":"LineWall","color":"0E"},{"type":"LineWall","color":"0E"},{"type":"Wall","color":"0E"},{"type":"Wall","color":"0E"},{"type":"Wall","color":"0E"},{"type":"Wall","color":"0E"},{"type":"Wall","color":"0E"},{},{"type":"Wall","color":"0E"},{"type":"Wall","color":"0E"},{"type":"Boulder","color":"0E"},{"type":"Wall","color":"0E"},{"type":"Wall","color":"0E"},{},{"type":"Wall","color":"0E"},{"type":"Wall","color":"0E"},{"type":"Wall","color":"0E"},{"type":"Wall","color":"0E"},{"type":"Wall","color":"0E"},{"type":"LineWall","color":"0E"},{"type":"LineWall","color":"0E"},{"type":"LineWall","color":"0E"},{"type":"LineWall","color":"0E"},{"type":"LineWall","color":"0E"},{"type":"Boulder","color":"0E"},{"type":"LineWall","color":"0E"},{"type":"LineWall","color":"0E"},{"type":"LineWall","color":"0E"},{"type":"LineWall","color":"0E"},{"type":"LineWall","color":"0E"},{"type":"Wall","color":"0E"},{},{},{},{},{"type":"Gem","color":"0D"},{"type":"Gem","color":"0D"},{"type":"Gem","color":"0D"},{},{},{},{},{"type":"Wall","color":"0E"},{"type":"Tiger","color":"0B","speed":2,"intelligence":5,"firingRate":5},{"type":"Tiger","color":"0B","speed":2,"intelligence":5,"firingRate":5},{"type":"Tiger","color":"0B","speed":2,"intelligence":5,"firingRate":5},{"type":"Wall","color":"0E"},{},{"type":"Wall","color":"0E"},{"type":"Gem","color":"0D"},{"type":"Gem","color":"0D"},{"type":"Gem","color":"0D"},{"type":"Wall","color":"0E"},{},{"type":"Wall","color":"0E"},{"type":"Tiger","color":"0B","speed":2,"intelligence":5,"firingRate":5},{"type":"Tiger","color":"0B","speed":2,"intelligence":5,"firingRate":5},{"type":"Tiger","color":"0B","speed":2,"intelligence":5,"firingRate":5},{"type":"Wall","color":"0E"},{},{},{},{},{"type":"Gem","color":"0D"},{"type":"Gem","color":"0D"},{"type":"Gem","color":"0D"},{},{},{},{"type":"Wall","color":"0E"},{"type":"Wall","color":"0E"},{},{},{},{},{"type":"Gem","color":"0D"},{"type":"Gem","color":"0D"},{"type":"Gem","color":"0D"},{},{},{},{},{"type":"BreakableWall","color":"0B"},{"type":"Tiger","color":"0B","speed":2,"intelligence":5,"firingRate":5},{"type":"Tiger","color":"0B","speed":2,"intelligence":5,"firingRate":5},{"type":"Tiger","color":"0B","speed":2,"intelligence":5,"firingRate":5},{"type":"Wall","color":"0E"},{"type":"Door","color":"1F","doorId":"1","targetBoard":"Test"},{"type":"Wall","color":"0E"},{"type":"Gem","color":"0D"},{"type":"Gem","color":"0D"},{"type":"Gem","color":"0D"},{"type":"Wall","color":"0E"},{},{"type":"Wall","color":"0E"},{"type":"Tiger","color":"0B","speed":2,"intelligence":5,"firingRate":5},{"type":"Tiger","color":"0B","speed":2,"intelligence":5,"firingRate":5},{"type":"Tiger","color":"0B","speed":2,"intelligence":5,"firingRate":5},{"type":"BreakableWall","color":"0B"},{},{},{},{},{"type":"Gem","color":"0D"},{"type":"Gem","color":"0D"},{"type":"Gem","color":"0D"},{},{},{},{"type":"Wall","color":"0E"},{"type":"Wall","color":"0E"},{"type":"Wall","color":"0E"},{"type":"Wall","color":"0E"},{"type":"Wall","color":"0E"},{"type":"Wall","color":"0E"},{"type":"Wall","color":"0E"},{"type":"Wall","color":"0E"},{"type":"Wall","color":"0E"},{"type":"Wall","color":"0E"},{"type":"Wall","color":"0E"},{"type":"Wall","color":"0E"},{"type":"Wall","color":"0E"},{"type":"Wall","color":"0E"},{"type":"Wall","color":"0E"},{"type":"Wall","color":"0E"},{"type":"Wall","color":"0E"},{"type":"Wall","color":"0E"},{"type":"Wall","color":"0E"},{"type":"Wall","color":"0E"},{"type":"Wall","color":"0E"},{"type":"Wall","color":"0E"},{"type":"Wall","color":"0E"},{"type":"Wall","color":"0E"},{"type":"Wall","color":"0E"},{"type":"Wall","color":"0E"},{"type":"Wall","color":"0E"},{"type":"Wall","color":"0E"},{"type":"Wall","color":"0E"},{"type":"Wall","color":"0E"},{"type":"Wall","color":"0E"},{"type":"Wall","color":"0E"},{"type":"Wall","color":"0E"},{"type":"Wall","color":"0E"},{"type":"Wall","color":"0E"},{"type":"Wall","color":"0E"},{"type":"Wall","color":"0E"},{"type":"Wall","color":"0E"},{"type":"Wall","color":"0E"},{"type":"Wall","color":"0E"},{"type":"Wall","color":"0E"}],"scripts":[]},{"name":"Test","playerX":20,"playerY":7,"width":40,"height":15,"tiles":[{"type":"Wall","color":"0E"},{"type":"Wall","color":"0E"},{"type":"Wall","color":"0E"},{"type":"Wall","color":"0E"},{"type":"Wall","color":"0E"},{"type":"Wall","color":"0E"},{"type":"Wall","color":"0E"},{"type":"Wall","color":"0E"},{"type":"Wall","color":"0E"},{"type":"Wall","color":"0E"},{"type":"Wall","color":"0E"},{"type":"Wall","color":"0E"},{"type":"Wall","color":"0E"},{"type":"Wall","color":"0E"},{"type":"Wall","color":"0E"},{"type":"Wall","color":"0E"},{"type":"Wall","color":"0E"},{"type":"Wall","color":"0E"},{"type":"Wall","color":"0E"},{"type":"Wall","color":"0E"},{"type":"Wall","color":"0E"},{"type":"Wall","color":"0E"},{"type":"Wall","color":"0E"},{"type":"Wall","color":"0E"},{"type":"Wall","color":"0E"},{"type":"Wall","color":"0E"},{"type":"Wall","color":"0E"},{"type":"Wall","color":"0E"},{"type":"Wall","color":"0E"},{"type":"Wall","color":"0E"},{"type":"Wall","color":"0E"},{"type":"Wall","color":"0E"},{"type":"Wall","color":"0E"},{"type":"Wall","color":"0E"},{"type":"Wall","color":"0E"},{"type":"Wall","color":"0E"},{"type":"Wall","color":"0E"},{"type":"Wall","color":"0E"},{"type":"Wall","color":"0E"},{"type":"Wall","color":"0E"},{"type":"Wall","color":"0E"},{},{"type":"LineWall","color":"0E"},{},{},{},{},{},{},{},{},{},{},{},{"type":"LineWall","color":"0E"},{},{},{},{},{},{},{},{},{},{},{},{},{},{},{},{},{},{},{},{},{},{},{},{},{"type":"Wall","color":"0E"},{"type":"Wall","color":"0E"},{},{"type":"LineWall","color":"0E"},{},{},{},{},{},{},{},{},{},{},{},{"type":"LineWall","color":"0E"},{},{},{},{},{},{},{},{},{},{},{},{},{},{},{},{},{},{},{},{},{},{},{},{},{"type":"Wall","color":"0E"},{"type":"Wall","color":"0E"},{},{"type":"LineWall","color":"0E"},{},{"type":"Ruffian","color":"0D","speed":1,"intelligence":5,"restingTime":5},{"type":"Ruffian","color":"0D","speed":1,"intelligence":5,"restingTime":5},{"type":"Ruffian","color":"0D","speed":1,"intelligence":5,"restingTime":5},{"type":"Ruffian","color":"0D","speed":1,"intelligence":5,"restingTime":5},{"type":"Ruffian","color":"0D","speed":1,"intelligence":5,"restingTime":5},{"type":"Ruffian","color":"0D","speed":1,"intelligence":5,"restingTime":5},{"type":"Ruffian","color":"0D","speed":1,"intelligence":5,"restingTime":5},{"type":"Ruffian","color":"0D","speed":1,"intelligence":5,"restingTime":5},{},{},{"type":"BreakableWall","color":"0B"},{},{},{},{},{},{},{},{},{},{},{},{},{},{"type":"Door","color":"1F","doorId":"1","targetBoard":"Untitled"},{},{},{},{},{},{},{},{},{},{},{"type":"Wall","color":"0E"},{"type":"Wall","color":"0E"},{},{"type":"LineWall","color":"0E"},{},{"type":"Ruffian","color":"0D","speed":1,"intelligence":5,"restingTime":5},{"type":"Ruffian","color":"0D","speed":1,"intelligence":5,"restingTime":5},{"type":"Ruffian","color":"0D","speed":1,"intelligence":5,"restingTime":5},{"type":"Ruffian","color":"0D","speed":1,"intelligence":5,"restingTime":5},{"type":"Ruffian","color":"0D","speed":1,"intelligence":5,"restingTime":5},{"type":"Ruffian","color":"0D","speed":1,"intelligence":5,"restingTime":5},{"type":"Ruffian","color":"0D","speed":1,"intelligence":5,"restingTime":5},{"type":"Ruffian","color":"0D","speed":1,"intelligence":5,"restingTime":5},{},{},{"type":"BreakableWall","color":"0B"},{},{},{},{},{},{},{},{"type":"Spider","color":"0C","speed":1,"under":{"type":"SpiderWeb","color":"08"}},{},{},{},{},{},{},{},{},{},{},{},{},{},{},{},{},{"type":"Wall","color":"0E"},{"type":"Wall","color":"0E"},{},{"type":"LineWall","color":"0E"},{},{},{},{},{},{},{},{},{},{},{},{"type":"LineWall","color":"0E"},{"type":"SpiderWeb","color":"08"},{"type":"SpiderWeb","color":"08"},{"type":"SpiderWeb","color":"08"},{"type":"SpiderWeb","color":"08"},{"type":"SpiderWeb","color":"08"},{"type":"SpiderWeb","color":"08"},{"type":"SpiderWeb","color":"08"},{"type":"SpiderWeb","color":"08"},{"type":"SpiderWeb","color":"08"},{"type":"SpiderWeb","color":"08"},{"type":"SpiderWeb","color":"08"},{"type":"SpiderWeb","color":"08"},{"type":"SpiderWeb","color":"08"},{"type":"SpiderWeb","color":"08"},{"type":"SpiderWeb","color":"08"},{"type":"SpiderWeb","color":"08"},{"type":"SpiderWeb","color":"08"},{"type":"SpiderWeb","color":"08"},{"type":"SpiderWeb","color":"08"},{},{"type":"SpinningGun","color":"0E","speed":2,"intelligence":5,"firingRate":5},{},{},{},{"type":"Wall","color":"0E"},{"type":"Wall","color":"0E"},{},{"type":"LineWall","color":"0E"},{"type":"LineWall","color":"0E"},{"type":"LineWall","color":"0E"},{"type":"LineWall","color":"0E"},{"type":"LineWall","color":"0E"},{"type":"LineWall","color":"0E"},{"type":"LineWall","color":"0E"},{"type":"LineWall","color":"0E"},{"type":"LineWall","color":"0E"},{"type":"LineWall","color":"0E"},{"type":"LineWall","color":"0E"},{"type":"LineWall","color":"0E"},{"type":"LineWall","color":"0E"},{},{},{},{},{},{},{},{},{},{},{},{},{},{},{},{},{},{},{"type":"SpiderWeb","color":"08"},{},{},{},{},{},{"type":"Wall","color":"0E"},{"type":"Wall","color":"0E"},{},{},{},{},{},{},{},{},{},{},{},{},{},{},{},{},{},{},{},{"color":"1F","speed":1},{"type":"SpiderWeb","color":"08"},{"type":"SpiderWeb","color":"08"},{"type":"SpiderWeb","color":"08"},{"type":"SpiderWeb","color":"08"},{"type":"SpiderWeb","color":"08"},{"type":"SpiderWeb","color":"08"},{"type":"SpiderWeb","color":"08"},{"type":"SpiderWeb","color":"08"},{"type":"SpiderWeb","color":"08"},{"type":"SpiderWeb","color":"08"},{"type":"SpiderWeb","color":"08"},{"type":"SpiderWeb","color":"08"},{"type":"SpiderWeb","color":"08"},{},{},{},{},{},{"type":"Wall","color":"0E"},{"type":"Wall","color":"0E"},{},{"type":"Bear","color":"06","speed":2,"sensitivity":9},{"type":"Bear","color":"06","speed":2,"sensitivity":9},{"type":"Bear","color":"06","speed":2,"sensitivity":9},{},{},{},{},{},{},{"type":"BreakableWall","color":"0B"},{"type":"BreakableWall","color":"0B"},{"type":"BreakableWall","color":"0B"},{"type":"BreakableWall","color":"0B"},{},{},{},{},{},{},{"type":"SpiderWeb","color":"08"},{},{},{},{},{},{},{},{},{},{},{},{},{},{},{},{},{},{"type":"Wall","color":"0E"},{"type":"Wall","color":"0E"},{},{},{},{},{},{},{},{},{},{},{},{},{},{},{},{},{},{},{},{},{"type":"SpiderWeb","color":"08"},{},{"type":"Boulder","color":"0E"},{"type":"LineWall","color":"0E"},{"type":"LineWall","color":"0E"},{"type":"LineWall","color":"0E"},{"type":"LineWall","color":"0E"},{"type":"LineWall","color":"0E"},{"type":"LineWall","color":"0E"},{"type":"LineWall","color":"0E"},{"type":"LineWall","color":"0E"},{"type":"LineWall","color":"0E"},{},{},{},{},{},{},{"type":"Wall","color":"0E"},{"type":"Wall","color":"0E"},{},{},{},{},{},{},{},{},{},{},{},{},{},{},{},{"type":"Spider","color":"0C","speed":1,"under":{"type":"SpiderWeb","color":"08"}},{},{},{"type":"SpiderWeb","color":"08"},{"type":"SpiderWeb","color":"08"},{"type":"SpiderWeb","color":"08"},{},{"type":"Boulder","color":"0E"},{"type":"Teleporter","color":"0E","speed":3,"orientation":"East"},{"type":"Ammo","color":"03"},{"type":"Gem","color":"0D"},{"type":"Ammo","color":"03"},{"type":"Gem","color":"0D"},{"type":"Ammo","color":"03"},{"type":"Gem","color":"0D"},{"type":"Ammo","color":"03"},{"type":"Teleporter","color":"0E","speed":3,"orientation":"East"},{},{},{},{},{},{},{"type":"Wall","color":"0E"},{"type":"Wall","color":"0E"},{"type":"SpiderWeb","color":"08"},{"type":"SpiderWeb","color":"08"},{"type":"SpiderWeb","color":"08"},{"type":"SpiderWeb","color":"08"},{"type":"SpiderWeb","color":"08"},{},{},{"type":"SpiderWeb","color":"08"},{},{},{"type":"SpinningGun","color":"0E","speed":2,"intelligence":9,"firingRate":5},{},{},{},{"type":"SpiderWeb","color":"08"},{"type":"SpiderWeb","color":"08"},{"type":"SpiderWeb","color":"08"},{"type":"SpiderWeb","color":"08"},{"type":"SpiderWeb","color":"08"},{},{},{},{"type":"Boulder","color":"0E"},{"type":"LineWall","color":"0E"},{"type":"LineWall","color":"0E"},{"type":"LineWall","color":"0E"},{"type":"LineWall","color":"0E"},{"type":"LineWall","color":"0E"},{"type":"LineWall","color":"0E"},{"type":"LineWall","color":"0E"},{"type":"LineWall","color":"0E"},{"type":"LineWall","color":"0E"},{},{},{},{},{},{},{"type":"Wall","color":"0E"},{"type":"Wall","color":"0E"},{},{"type":"SpiderWeb","color":"08"},{},{},{"type":"SpiderWeb","color":"08"},{"type":"SpiderWeb","color":"08"},{"type":"SpiderWeb","color":"08"},{"type":"SpiderWeb","color":"08"},{"type":"SpiderWeb","color":"08"},{"type":"SpiderWeb","color":"08"},{"type":"SpiderWeb","color":"08"},{"type":"SpiderWeb","color":"08"},{"type":"SpiderWeb","color":"08"},{"type":"SpiderWeb","color":"08"},{"type":"SpiderWeb","color":"08"},{},{},{},{},{},{},{},{},{},{"type":"Teleporter","color":"0E","speed":3,"orientation":"East"},{"type":"LineWall","color":"0E"},{"type":"SolidWall","color":"0E"},{"type":"SolidWall","color":"0E"},{"type":"SolidWall","color":"0E"},{"type":"LineWall","color":"0E"},{"type":"Teleporter","color":"0E","speed":3,"orientation":"East"},{},{},{},{},{},{},{},{"type":"Wall","color":"0E"},{"type":"Wall","color":"0E"},{},{"type":"SpiderWeb","color":"08"},{},{},{},{"type":"Spider","color":"0C","speed":1,"under":{"type":"SpiderWeb","color":"08"}},{},{},{},{},{"type":"SpiderWeb","color":"08"},{},{},{},{},{},{},{},{},{},{},{},{},{"type":"LineWall","color":"0E"},{"type":"LineWall","color":"0E"},{"type":"LineWall","color":"0E"},{"type":"LineWall","color":"0E"},{"type":"LineWall","color":"0E"},{"type":"LineWall","color":"0E"},{"type":"LineWall","color":"0E"},{"type":"LineWall","color":"0E"},{"type":"LineWall","color":"0E"},{},{},{},{},{},{},{"type":"Wall","color":"0E"},{"type":"Wall","color":"0E"},{"type":"Wall","color":"0E"},{"type":"Wall","color":"0E"},{"type":"Wall","color":"0E"},{"type":"Wall","color":"0E"},{"type":"Wall","color":"0E"},{"type":"Wall","color":"0E"},{"type":"Wall","color":"0E"},{"type":"Wall","color":"0E"},{"type":"Wall","color":"0E"},{"type":"Wall","color":"0E"},{"type":"Wall","color":"0E"},{"type":"Wall","color":"0E"},{"type":"Wall","color":"0E"},{"type":"Wall","color":"0E"},{"type":"Wall","color":"0E"},{"type":"Wall","color":"0E"},{"type":"Wall","color":"0E"},{"type":"Wall","color":"0E"},{"type":"Wall","color":"0E"},{"type":"Wall","color":"0E"},{"type":"Wall","color":"0E"},{"type":"Wall","color":"0E"},{"type":"Wall","color":"0E"},{"type":"Wall","color":"0E"},{"type":"Wall","color":"0E"},{"type":"Wall","color":"0E"},{"type":"Wall","color":"0E"},{"type":"Wall","color":"0E"},{"type":"Wall","color":"0E"},{"type":"Wall","color":"0E"},{"type":"Wall","color":"0E"},{"type":"Wall","color":"0E"},{"type":"Wall","color":"0E"},{"type":"Wall","color":"0E"},{"type":"Wall","color":"0E"},{"type":"Wall","color":"0E"},{"type":"Wall","color":"0E"},{"type":"Wall","color":"0E"},{"type":"Wall","color":"0E"}],"scripts":[]}]}